qilum/__init__.py
qilum/stats.py
qilum/tests/__init__.py
qilum/tests/qilum_test.py
qilum-1.0.0.dist-info/LICENSE.txt
qilum-1.0.0.dist-info/METADATA
qilum-1.0.0.dist-info/WHEEL
qilum-1.0.0.dist-info/top_level.txt
qilum-1.0.0.dist-info/RECORD
