Metadata-Version: 2.1
Name: qilum
Version: 1.0.0
Summary: Statistical supplementary package to numpy, scipy, ...
Home-page: https://www.qilum.com/
Author: Damien Loison
Author-email: loison.damien@gmail.com
License: UNKNOWN
Keywords: statistic random number generator scipy
Platform: UNKNOWN
Classifier: Programming Language :: Python :: 3
Classifier: License :: OSI Approved :: MIT License
Classifier: Operating System :: OS Independent
Requires-Python: >=3.6
Requires-Dist: numba
Requires-Dist: numpy
Requires-Dist: scipy
